RQQ
