Metadata-Version: 2.1
Name: RQQ
Version: 0.143
Summary: My CMD 模組
Home-page: UNKNOWN
License: LGPL
Platform: UNKNOWN
